__init__.py
nmldiff.py
icon_nmltools-0.1b0.dist-info/METADATA
icon_nmltools-0.1b0.dist-info/WHEEL
icon_nmltools-0.1b0.dist-info/entry_points.txt
icon_nmltools-0.1b0.dist-info/top_level.txt
icon_nmltools-0.1b0.dist-info/RECORD
