Metadata-Version: 2.1
Name: icon-nmltools
Version: 0.1b0
Summary: A collection of tools to compare and process ICON namelists
Author-email: Tobias Selz <tobias.selz@lmu.de>
License: BSD-3-Clause
Project-URL: Homepage, https://gitlab.physik.uni-muenchen.de/Tobias.Selz/icon-nmltools
Project-URL: Repository, https://gitlab.physik.uni-muenchen.de/Tobias.Selz/icon-nmltools
Classifier: Programming Language :: Python :: 3
Requires-Python: >=3.6
Requires-Dist: f90nml
